graphzoo/__init__.py
graphzoo/config.py
graphzoo/dataloader/__init__.py
graphzoo/dataloader/dataloader.py
graphzoo/dataloader/download.py
graphzoo/layers/__init__.py
graphzoo/layers/att_layers.py
graphzoo/layers/hyp_att_layers.py
graphzoo/layers/hyp_layers.py
graphzoo/layers/layers.py
graphzoo/manifolds/__init__.py
graphzoo/manifolds/base.py
graphzoo/manifolds/euclidean.py
graphzoo/manifolds/hyperboloid.py
graphzoo/manifolds/poincare.py
graphzoo/models/__init__.py
graphzoo/models/base_models.py
graphzoo/models/decoders.py
graphzoo/models/encoders.py
graphzoo/optimizers/__init__.py
graphzoo/optimizers/radam.py
graphzoo/optimizers/rsgd.py
graphzoo/trainers/__init__.py
graphzoo/trainers/train.py
graphzoo/utils/__init__.py
graphzoo/utils/eval_utils.py
graphzoo/utils/math_utils.py
graphzoo/utils/train_utils.py
graphzoo-0.0.1.dist-info/METADATA
graphzoo-0.0.1.dist-info/WHEEL
graphzoo-0.0.1.dist-info/licenses/LICENSE
graphzoo-0.0.1.dist-info/RECORD
