Metadata-Version: 2.1
Name: graphzoo
Version: 0.0.1
Summary: A hyperbolic toolkit
Project-URL: Homepage, https://github.com/AnoushkaVyas/GraphZoo
Project-URL: Bug Tracker, https://github.com/AnoushkaVyas/GraphZoo
Author-email: Anoushka Vyas <anoushkavyas@gmail.com>
License: MIT License
Classifier: License :: OSI Approved :: MIT License
Classifier: Operating System :: OS Independent
Classifier: Programming Language :: Python :: 3
Requires-Python: >=3.5
